compmusic/__init__.py
compmusic/_version.py
compmusic/dunya/__init__.py
compmusic/dunya/andalusian.py
compmusic/dunya/carnatic.py
compmusic/dunya/conn.py
compmusic/dunya/docserver.py
compmusic/dunya/hindustani.py
compmusic/dunya/jingju.py
compmusic/dunya/makam.py
compmusic-0.4.dist-info/LICENSE
compmusic-0.4.dist-info/METADATA
compmusic-0.4.dist-info/WHEEL
compmusic-0.4.dist-info/top_level.txt
compmusic-0.4.dist-info/RECORD
