Metadata-Version: 2.1
Name: compmusic
Version: 0.4
Summary: API client for accessing data from Dunya
Author-email: "Music Technology Group, Universitat Pompeu Fabra" <mtg-info@upf.edu>
Project-URL: Homepage, https://github.com/MTG/pycompmusic/
Classifier: Programming Language :: Python :: 3
Classifier: License :: OSI Approved :: MIT License
Classifier: Operating System :: OS Independent
Requires-Python: >=3.8
License-File: LICENSE
Requires-Dist: requests
